{
    "repo": "socketio/socket.io",
    "url": "https://github.com/socketio/socket.io",
    "branch": "master",
    "configs": [
        {
            "package": "basic-crud-server",
            "lang": "js",
            "dir": "examples/basic-crud-application/server/test",
            "framework": "mocha",
            "pattern": "**/*.{js,ts}"
        },
        {
            "package": "socket.io",
            "lang": "ts",
            "dir": "test",
            "framework": "mocha",
            "pattern": "**/*.{js,ts}"
        }
    ]
}